aidev_wxbot/__init__.py
aidev_wxbot/apps.py
aidev_wxbot/settings.py
aidev_wxbot/urls.py
aidev_wxbot/api/__init__.py
aidev_wxbot/api/bkaidev.py
aidev_wxbot/context/__init__.py
aidev_wxbot/context/message.py
aidev_wxbot/utils/__init__.py
aidev_wxbot/utils/rabbitmq.py
aidev_wxbot/wxaibot/__init__.py
aidev_wxbot/wxaibot/context.py
aidev_wxbot/wxaibot/views.py
aidev_wxbot/wxaibot/decryption/__init__.py
aidev_wxbot/wxaibot/decryption/ierror.py
aidev_wxbot-1.0.9.dist-info/METADATA
aidev_wxbot-1.0.9.dist-info/WHEEL
aidev_wxbot-1.0.9.dist-info/entry_points.txt
aidev_wxbot-1.0.9.dist-info/RECORD
